{"20210624112029":{"id":"20210624112029","nombre":"Gian","precio":"","categoria":"CATEGORIA1","marca":"Adidas","activa":"TRUE","descripcion":"    ","imagen":[""]},"20210624112113":{"id":"20210624112113","nombre":"PRODUCTO PRUIEBA","precio":"","categoria":"CATEGORIA1","marca":"Adidas","activa":"FALSE","descripcion":"  ","imagen":[""]},"20210624112132":{"id":"20210624112132","nombre":"PRODUCTO PRUEBA","precio":"","categoria":"CATEGORIA1","marca":"Adidas","activa":"TRUE","descripcion":"    ","imagen":[""]}}