{"20210619041312":{"id":"20210619041312","nombre":"Prueba","precio":"4500","categoria":"Gian","marca":"UNDER ARMOUR","activa":"TRUE","descripcion":"                          ","imagen":null},"20210619044110":{"id":"20210619044110","nombre":"Azul","precio":"5","categoria":"Remeras","marca":"Adidas","activa":"TRUE","descripcion":"          ","imagen":null},"20210619053835":{"id":"20210619053835","nombre":"PRUEBA MARCA","precio":"69","categoria":"Pantalones","marca":"Adidas","activa":"TRUE","descripcion":"  prueba marca ","imagen":null}}